{"skills": ["storage management", "javascript", "management", "unit test", "io", "bluetooth", "git", "rail", "ruby", "swift", "trello", "asset management", "website development", "css", "jira", "mvvm", "le", "kif", "testing", "objective c", "class", "process development", "bitbucket", "agile"], "fulltext": "NH\u01af PHAN \nSOFTWARE DEVELOPER \nSUMMARY \nInnovative IT developer offers deep experiences to make softwares with highly effective and creative \nsolutions to resolve technology challenges. \nCORE COMPETENCIES \niOS - Objective-C \niOS - Swift \nTeam work - Scrum \nAgile development \nFamiliar with JIRA, Trello, \nPivotal.         \n\u2022 \nSource code \nversioning: Bitbucket, Git \n\u2022 \nEnglish communication \n\u2022 \nWorking independent \n\u2022 \nWorking in high pressure \n\u2022 \nWorking with the server \nside. \n\u2022 \nPair programming \n\u2022 \n\u2022 \n\u2022 \n\u2022 \n\u2022 \nEDUCATION \n2007 - 2010 \nLe Khiet High school \nSpecial Informatics class \n2010 - 2014 \nUniversity of Science, Ho Chi Minh city \nHonor program  \nDEVELOPER EXPERIENCE \n2018 - now \nNeptune PPA (East Agile) \niOS Developer \nhttps://itunes.apple.com/us/app/neptuneppa/id1360631281 ?mt=8 \nI own this project. It's written in swift, using MVVM architecture. \nThe special thing is the UI made by coding totally without Storyboard.  \nBuilding up this project from scratch. \nTraining juniors. \nUnit test and integration test using KIF and MockingJay. \n2017 - 2018 \nBBM (East Agile) \n\u2022 \n\u2022 \n\u2022 \niOS developer \nhttps://itunes.apple.com/vn/app/bbm/id690046600?mt=8 \nThis is the biggest application I worked in so far. There are many pillars in this project. Two pillars I \nworked in: \n- Asset Sharing: relating Chat, messages type, asset management, The biggest feature I owned is \nStorage management that allows user managing their assets, messages.  \n- Virtual goods: relating Stickers store and the third-party BBMoji application (custom sticker maker). \nIn this pillar, My main work is to maintain and add new features. \n\u2022 \nLearning and working with Agile Development Process and Pair Programming as well. \n\u2022 \nWriting Unit tests and Integration test. \n\u2022 \nMocking data, make the code testable.  \n2016 - 2017 \nHeadlne, Kid-villages, Araliya - Dating App \niOS developer \nhttps://itunes.apple.com/vn/app/headlne-best-news-app/id1072545214 ?mt=8 \nhttps://itunes.apple.com/us/app/araliya-liyathabara-com/id1313580566 \nhttps://itunes.apple.com/vn/app/trump-headlne/id1121448732 ?mt=8 \nhttps://itunes.apple.com/vn/app/kidzville-kellyville/id1185352937 ?mt=8 \n- Headlne project: My responsibility is maintaining, adding new features. \n- Kid-villages project: Building up from scratch and developing the new social application for day-care \ncenter.  \n- Araliya project: Building up and developing the dating application. \n\u2022 \nUsing Cloudinary, Photo library. \n\u2022 \nUsing Socket to do chatting. \n\u2022 \nEncrypt/decrypt data. \n\u2022 \nBuilding up and structuring projects from scratch by myself. \n2016 - 2017 \nSCUTIFY \niOS Developer \nhttps://itunes.apple.com/vn/app/scutify-passionate-investors-traders/id673974489?mt=8 \nWorked on this project that gives me a chance to know more about iOS development by studying \nand applying storyboard to iOS project rather than using 100% code in previous projects. \n\u2022 \nWorking with trading SDK. \n\u2022 \nCoding using storyboard. \n2014 - 2016 \nMisfit Wearables (Fossil Viet Nam) \niOS Developer \nhttps://itunes.apple.com/vn/app/misfit-link/id1010611810 ?mt=8 \nThis is an international company that produces smart devices connecting with the phone via \nBluetooth. Main work is making a new application, adding new features and maintaining. \nStudied deeply in Objective-C language. \nBe trained by professional seniors. \nStudied Objective-C. \nStudied Swift language. \nDeveloped and maintained Misfit LINK - One of three main Misfit's applications. \nDeveloped some internal applications for testing devices, demonstrations. \nTraining-trip in the USA and taking part in two biggest technology events (WWDC 2016 and GOOGLE \nI/O 2016). \n\u2022 \n\u2022 \n\u2022 \n\u2022 \n\u2022 \n\u2022 \n\u2022 \n2013 - 2014 \nLARION COMPUTER \nWeb Developer \nThis is my first company which provided opportunities to study new technology: Ruby/Rails. \n\u2022 \nFrontend: CSS, Javascript, HAML. \n\u2022 \nStudied about testing and quality of software. \n\u2022 \nStudied and worked with new language Ruby. ", "educations": [{"id": 4560, "gpa": null, "major": "Bi\u1ec3u di\u1ec5n nh\u1ea1c c\u1ee5 ph\u01b0\u01a1ng t\u00e2y", "school": "Le Khiet High school", "diploma": "Other", "end_time": "2010-01-01T00:00:00Z", "conf_score": 0.9243038686172426, "start_time": "2007-01-01T00:00:00Z", "picklist_major": "Art/Design", "major_categories": "Ngh\u1ec7 thu\u1eadt", "major_categories_detail": "Ngh\u1ec7 thu\u1eadt tr\u00ecnh di\u1ec5n"}, {"id": 4561, "gpa": null, "major": null, "school": "University of Science, Ho Chi Minh city", "diploma": "Bachelors", "end_time": "2014-01-01T00:00:00Z", "conf_score": 0.7739975218033928, "start_time": "2010-01-01T00:00:00Z", "picklist_major": "Other", "major_categories": "", "major_categories_detail": ""}], "experiences": [{"id": 15193, "detail": "https://itunes.apple.com/us/app/neptuneppa/id1360631281 ?mt=8\nI own this project. It's written in swift, using MVVM architecture.\nThe special thing is the UI made by coding totally without Storyboard. Building up this project from scratch.\nTraining juniors.\nUnit test and integration test using KIF and MockingJay.", "company": "Neptune PPA (East Agile)", "end_time": "2023-04-13T00:00:00Z", "industry": "Other", "position": "iOS Developer", "conf_score": 0.905945861725067, "start_time": "2018-01-01T00:00:00Z"}, {"id": 15194, "detail": "https://itunes.apple.com/vn/app/bbm/id690046600?mt=8\nThis is the biggest application I worked in so far. There are many pillars in this project. Two pillars I worked in:\n- Asset Sharing: relating Chat, messages type, asset management, The biggest feature I owned is\nStorage management that allows user managing their assets, messages.\n- Virtual goods: relating Stickers store and the third-party BBMoji application (custom sticker maker).\nIn this pillar, My main work is to maintain and add new features.\nLearning and working with Agile Development Process and Pair Programming as well.\nWriting Unit tests and Integration test.\nMocking data, make the code testable.", "company": "BBM (East Agile)", "end_time": "2018-01-31T00:00:00Z", "industry": "Other", "position": "iOS developer", "conf_score": 0.830738895005311, "start_time": "2017-01-01T00:00:00Z"}, {"id": 15195, "detail": "ttps://itunes.apple.com/vn/app/headlne-best-news-app/id1072545214 ?mt=8 https://itunes.apple.com/us/app/araliya-liyathabara-com/id1313580566 https://itunes.apple.com/vn/app/trump-headlne/id1121448732 ?mt=8 https://itunes.apple.com/vn/app/kidzville-kellyville/id1185352937 ?mt=8\n- Headlne project: My responsibility is maintaining, adding new features.\n- Kid-villages project: Building up from scratch and developing the new social application for day-care center.\n- Araliya project: Building up and developing the dating application.\nUsing Cloudinary, Photo library.\nUsing Socket to do chatting.\nEncrypt/decrypt data.\nBuilding up and structuring projects from scratch by myself.\n\u2022 \u2022 \u2022 \u2022", "company": "Headlne, Kid - villages, Araliya - Dating App", "end_time": "2017-01-31T00:00:00Z", "industry": "Other", "position": "iOS developer", "conf_score": 0.8200858132399902, "start_time": "2016-01-01T00:00:00Z"}, {"id": 15196, "detail": "This is my first company which provided opportunities to study new technology: Ruby/Rails.", "company": "LARION COMPUTER", "end_time": "2014-01-31T00:00:00Z", "industry": "Other", "position": "Web Developer", "conf_score": 0.9183582400290474, "start_time": "2013-01-01T00:00:00Z"}], "address": null}