{"skills": ["angular", "css3", "ant design", "babel", "javascript", "c#", "es6", "database management", "sales", "management", "redux", "banking", "ant", "unit test", "object oriented", "entity framework", "git", "finance", "svn", "html5", "typescript", "redux saga", "database management system", "asp", "desktop", "verbal communication", "website development", "design pattern", "sql", "oop", "alarm system", "mvc", "jest", "reactjs", "desktop application", "twitter", "database", "angular 2", "process development", "clarify", "oracle", "teamwork", "arm solution", "gulp", "wcf", "problem solving", "bootstrap", "m sql server", "agile", "mysql", "jquery"], "fulltext": "Do Dinh Anh \nWeb Developer \nGender: Male \nPhone: +84 987.196.695 \nEmail: dinhanhdo95@gmail.com \nSUMMARY \nI'm Do Dinh Anh, a web developer with 2 years of experience in JavaScript and .NET \ntechnologies, with good knowledge of Object-Oriented and Design Patterns.  \nLearning new languages and technologies is what I\u2019m really keen on. I\u2019m considered a team-\nplayer because I prefer to discuss innovative ideas with others and tend to work well within the group. \nTECHNICAL SKILLS \n\u2022 \nProgramming Languages: \n- \nJavaScript, C#.NET \n- \nHTML5, CSS3 \n\u2022 \nFrameworks/ Platforms: \n- \nReactJS, Angular \n- \nWebpack, Gulp, Babel \n- \nES6, Typescript \n- \njQuery, Sass, Twitter Bootstrap \n- \nASP.NET MVC, Web API \n- \nEntity Framework \n\u2022 \nDatabase Management Systems: \n- \nMS SQL Server, MySQL \n\u2022 \nVersion Control: \n- \nGit, SVN \n\u2022 \nForeign Languages: \nEnglish: \n- \nGood reading/writing \n- \nBasic verbal communication \n\u2022 \nSoft Skills: \n- \nTime management \n- \nProblem solving \n- \nTeamwork \n\u2022 \nOthers: \n- \nGood understanding of OOP methodologies \n- \nExperience with Agile and Scrum development process \nWorking Experiences  \nWeb Developer / NTQ Solution \n\u2022 \nProject: Serimu Jvideos \n03/2019 \u2013 10/2019 \n- \nProject Description: An enhanced experience video system. It attracts creators and \nmakers to join the system so that they can improve, contribute to it and then viewers \ncan enjoy and wind down whenever they want. \n- \nTeam Size: 22 \n- \nResponsibilities: \nCommunicate with customers and teammates to clarify requirements \nDevelop key modules of the system that saved around 20% of the development \ntime of other functionalities \n- \nTechnologies: ReactJS, Redux, Webpack, Sass, Ant Design \n\u2022 \nProject: Pronexus-Works \n12/2018 \u2013 03/2019 \n- \nProject Description: Develop a local desktop application, it\u2019s one of a system lies in \na huge ecosystem of the organization that is taking up 60% of finance in the \nJapanese market and manages tons of documents and links related to that field. \n- \nTeam Size: 7 \n- \nResponsibilities: \nAnalyze specifications and recommend the best solutions to the customer \nDesign screens and build up features based on requirements  \n- \nTechnologies: WPF, WCF, Telerik UI, Oracle Database \nProject: M-Solutions ARMS \n08/2018 \u2013 12/2018 \n- \nProject Description: Dealing with the client side of a firing alarm system so that the \ncustomer can completely be in control of problems accurately. \n- \nTeam Size: 6 \n- \nResponsibilities: \nCommunicate with customers and teammates to report daily works \nBuild up features and implement unit tests based on requirements \n- \nTechnologies: ReactJS, Redux, Saga, ImmutableJS, Reselect, Jest \nProject: M-Solutions Sale System \n05/2018 \u2013 08/2018 \n- \nProject Description: Develop a sale and customer management system. Which has \nhighly complicated kind of banking business \n- \nTeam Size: 18 \n- \nResponsibilities: \nBuild screens according to specifications \nInteract data across sophisticatedly existing services \nWrite test cases and execute them \n- \nTechnologies: Dynamics 365, jQuery, JavaScript, CSS3, HTML5 \nJunior Developer / PowerGate Software \nProject: OneIT Mobile \n11/2017 \u2013 04/2018 \n\u2022 \n\u2022 \n\u2022 \n- \nProject Description: Develop a mobile management system. To better assist \ncustomers that can quickly give options and select suitable mobile phones \nconveniently. \n- \nTeam Size: 3 \n- \nResponsibilities: \nCommunicate with customers to get clear requirements \nCompose APIs and evolve modules of the system \n- \nTechnologies: Angular 2, HTML5, CSS3, ASP.NET Web API, Entity Framework, MS SQL \nServer \nProject: OneIT CoventryCRM \n06/2017 \u2013 11/2017 \n- \nProject Description: A meeting management application supports people to book \ntheir customer's appointments with anyone whenever they want, from wherever \nyou are. \n- \nTeam Size: 6 \n- \nResponsibilities: \nCommunicate with customers and teammates to get clear requirements \nDevelop the frameworks and modules of the system \n- \nTechnologies: Angular 2, HTML5, CSS3, Bootstrap 3 \n\u2022 \nEducation and Qualification \n\u2022 \n2014 \u2013 2018 \n- \nCertification: Engineering \n- \nLearning in: Posts and Telecommunications Institute of Technology, Vietnam \n- \nSpecialized in: Information Technology \n\u2022 \n2018 \u2013 2019 \n- \nCertification: Agile Developers \n- \nLearning in: Agile Academy, Vietnam \n- \nSpecialized in: Information Technology ", "educations": [{"id": 5398, "gpa": null, "major": "C\u00f4ng ngh\u1ec7 th\u00f4ng tin", "school": "Posts and Telecommunications Institute of Technology", "diploma": "Other", "end_time": "2018-01-01T00:00:00Z", "conf_score": 0.9201489608858643, "start_time": "2014-01-01T00:00:00Z", "picklist_major": "IT - Hardware/Networking", "major_categories": "M\u00e1y t\u00ednh v\u00e0 c\u00f4ng ngh\u1ec7 th\u00f4ng tin", "major_categories_detail": "C\u00f4ng ngh\u1ec7 th\u00f4ng tin"}], "experiences": [{"id": 18052, "detail": "- Project Description: An enhanced experience video system. It attracts creators and makers to join the system so that they can improve, contribute to it and then viewers can enjoy and wind down whenever they want.\n- Team Size: 22 Responsibilities: Communicate with customers and teammates to clarify requirements\nDevelop key modules of the system that saved around 20% of the development time of other functionalities\nTechnologies: ReactJS, Redux, Webpack, Sass, Ant Design", "company": "NTQ Solution", "end_time": "2019-10-31T00:00:00Z", "industry": "High Technology", "position": "Web Developer", "conf_score": 0.9175172730272324, "start_time": "2019-03-01T00:00:00Z"}, {"id": 18053, "detail": "Project: M-Solutions ARMS 08/2018 - 12/2018 - Project Description: Dealing with the client side of a firing alarm system so that the customer can completely be in control of problems accurately.\n- Team Size: 6 - Responsibilities: Communicate with customers and teammates to report daily works\nBuild up features and implement unit tests based on requirements\n- Technologies: ReactJS, Redux, Saga, ImmutableJS, Reselect, Jest", "company": "M - Solutions ARMS", "end_time": "2018-12-31T00:00:00Z", "industry": "High Technology", "position": null, "conf_score": 0.6925429707670153, "start_time": "2018-08-01T00:00:00Z"}, {"id": 18054, "detail": "", "company": "PowerGate Software", "end_time": "2018-08-31T00:00:00Z", "industry": "High Technology", "position": "Junior Developer", "conf_score": 0.8445619462773374, "start_time": "2018-05-01T00:00:00Z"}, {"id": 18055, "detail": "", "company": "OneIT Mobile", "end_time": "2018-04-30T00:00:00Z", "industry": "High Technology", "position": null, "conf_score": 0.7357023794500924, "start_time": "2017-11-01T00:00:00Z"}, {"id": 18056, "detail": "- Project Description: A meeting management application supports people to book their customer's appointments with anyone whenever they want, from wherever you are.\n- Team Size: 6 - Responsibilities: Communicate with customers and teammates to get clear requirements\nDevelop the frameworks and modules of the system\n- Technologies: Angular 2, HTML5, CSS3, Bootstrap 3", "company": "OneIT CoventryCRM", "end_time": "2017-11-30T00:00:00Z", "industry": "High Technology", "position": null, "conf_score": 0.6925429707670153, "start_time": "2017-06-01T00:00:00Z"}], "address": null}