{"skills": ["css", "dependency injection", "dom", "extjs", "oauth", "rss", "full stack development", "ajax", "entity framework", "io", "ftp", "xml file", "angular", "orm", "sql", "sales", "stack", "javascript", "xamarin", "excel", "xml", "flutter", "jwt", "android", "management", "serilog", "asp"], "fulltext": "8/21/2019\nTr\u01b0\u01a1ng \u0110\u00ecnh T\u00fa \u2013 Full Stack Engineer \u00b7 Resume.io\nhttps://resume.io/r/fbIvkEplL 1/1\nTR\u01af\u01a0NG \u0110\u00ccNH T\u00da\nFull Stack Engineer\n0834190594\nPROFILE\nA\ufffder graduated, i've worked as a Full Stack developer at FSo\ufffd for 3 years. Familiar with .NET &\nfront-end, SQL server. Have knowledge with common web architecture & principles.\nEMPLOYMENT HISTORY\n.NET Developer at FPT So\ufffdware, H\u1ed3 Ch\u00ed Minh\nAugust 2016 \u2013 August 2019\nWorking on DMS (Distributor Management System) projects, reuse the framework of team to\nimplement functions, develop functions only.\nUsing ASP .NET to build Web APIs.\nAutofac for dependency injection.\nORM: Entity framework with code first, generate model with T4Template, some module\nuse Dapper.\nLogging with log4net.\nTransfer XML files using WinSCP via FTP, implement windows service jobs to sync data.\nFront-end: use ExtJS to create page, AJAX to call API.\nDesign & implement report use Telerik reporrt.\nUsing .NET Core to build backend framework based on build-in .NET Core APIs include OAuth,\nDI...\nBoth authenticate with JWT & authorize user permissions based on build-in middleware.\nLogging with Serilog to log system errors, otherwise return semantic validation\nexceptions via middleware.\nImplement import/export excel with dynamic template.\nFront-end: using Angular 6 for UI. Build & optimize custom common components such as\nGridView, Autocomplete... able to customize DOM with Client javascript, CSS, design\nsemantic layout.\nFamiliar with SQL Server, can optimize & analyze query.\nCoding mobile app use Flutter for sales with some functions such as  synchronizing data, scan\nbar code. Maintain Xamarin android application.\nAchieved FSOFT Quality Honor of quater 2018: key member take part in building framework\nhelp development more quickly.\nEDUCATION\nUniversity Of Science, H\u1ed3 Ch\u00ed Minh\nDecember 2013 \u2013 December 2016\nDegree: Good\nEXTRA-CURRICULAR ACTIVITIES\nBlood donation & company volunteer activities at FPT So\ufffdware, H\u1ed3 Ch\u00ed\nMinh\nAugust 2016 \u2013 August 2019\nDETAILS\n0834190594\ntutruong.se@gmail.com\nLANGUAGES\nEnglish\nHOBBIES\nReading book, research new\ntechnology, traveling, listen to\nmusic, swimming and do gym\nexcercises...", "educations": [{"id": 5623, "gpa": null, "major": null, "school": "University Of Science, H\u1ed3 Ch\u00ed Minh", "diploma": "Bachelors", "end_time": "2016-12-01T00:00:00Z", "conf_score": 0.7411424838253973, "start_time": "2013-12-01T00:00:00Z", "picklist_major": "Other", "major_categories": "", "major_categories_detail": ""}], "experiences": [{"id": 18792, "detail": "Working on DMS (Distributor Management System) projects, reuse the framework of team to implement functions, develop functions only.\nUsing ASP .NET to build Web APIs. Autofac for dependency injection.\nORM: Entity framework with code first, generate model with T4Template, some module use Dapper. Logging with log4net.\nTransfer XML files using WinSCP via FTP, implement windows service jobs to sync data.\nFront-end: use ExtJS to create page, AJAX to call API. Design & implement report use Telerik reporrt.\nUsing .NET Core to build backend framework based on build-in .NET Core APIs include OAuth, DI... Both authenticate with JWT & authorize user permissions based on build-in middleware.\nLogging with Serilog to log system errors, otherwise return semantic validation exceptions via middleware.\nImplement import/export excel with dynamic template.\nFront-end: using Angular 6 for UI. Build & optimize custom common components such as\nGridView, Autocomplete... able to customize DOM with Client javascript, CSS, design semantic layout.\nFamiliar with SQL Server, can optimize & analyze query.\nCoding mobile app use Flutter for sales with some functions such as synchronizing data, scan bar code. Maintain Xamarin android application.\nAchieved FSOFT Quality Honor of quater 2018: key member take part in building framework help development more quickly.", "company": "FPT So ware", "end_time": "2019-08-31T00:00:00Z", "industry": "High Technology", "position": ".NET Developer", "conf_score": 0.8384022261982151, "start_time": "2016-08-01T00:00:00Z"}], "address": null}